{"authorDailyContributionsMap":{"LF1928":[{"date":"2025-01-23","commitResults":[{"hash":"9d42befbe34b7304f1ad19d65f2edb35fe88065c","isMergeCommit":false,"messageTitle":"Rename main class and logo","messageBody":"","fileTypesAndContributionMap":{"java":{"insertions":11,"deletions":10}}},{"hash":"af4e8d8fef29cb65cb13bafea6b05417e5f25a57","isMergeCommit":false,"messageTitle":"Add greeting","messageBody":"","tags":["Level-0"],"fileTypesAndContributionMap":{"java":{"insertions":6,"deletions":0}}},{"hash":"6b1b4acd2f971f210c321fb0e639896ea17fd684","isMergeCommit":false,"messageTitle":"Add support for echo","messageBody":"","tags":["Level-1"],"fileTypesAndContributionMap":{"java":{"insertions":23,"deletions":2},"md":{"insertions":1,"deletions":1}}},{"hash":"3ba2dde44564087b68d7c7d222f33e2e67ed76de","isMergeCommit":false,"messageTitle":"Add suport for list and add","messageBody":"","fileTypesAndContributionMap":{"java":{"insertions":17,"deletions":1}}}]}]},"authorFileTypeContributionMap":{"LF1928":{"java":54,"md":1,"fxml":0,"sh":0,"bat":0,"gradle":0,"txt":0}},"authorContributionVariance":{"LF1928":634.7755},"authorDisplayNameMap":{"LF1928":"ZHAN.. FEI"}}
