{"authorDailyContributionsMap":{"crmlatte":[{"date":"2025-01-23","commitResults":[{"hash":"af33279fb6d3213530baffb24f1ba20a6c830bb5","isMergeCommit":false,"messageTitle":"change name, greet, and exit","messageBody":"","tags":["Level-0"],"fileTypesAndContributionMap":{"java":{"insertions":11,"deletions":1}}},{"hash":"cb7a08c300a8a9ff8ed1cf83c7924aa582f16029","isMergeCommit":false,"messageTitle":"echo","messageBody":"","tags":["Level-1"],"fileTypesAndContributionMap":{"java":{"insertions":19,"deletions":15}}},{"hash":"a907636940c5092c028aa65fef00d4c7fb1fd266","isMergeCommit":false,"messageTitle":"add, list","messageBody":"","tags":["Level-2"],"fileTypesAndContributionMap":{"java":{"insertions":35,"deletions":10}}}]},{"date":"2025-01-26","commitResults":[{"hash":"341ff8c8517daecd82391ecaa81418baafa483a3","isMergeCommit":false,"messageTitle":"mark as done/undone","messageBody":"","tags":["Level-3"],"fileTypesAndContributionMap":{"java":{"insertions":79,"deletions":27}}},{"hash":"9d19abf7f475cc2782021da41997832d62696b19","isMergeCommit":false,"messageTitle":"todo, event, deadline","messageBody":"","tags":["Level-4"],"fileTypesAndContributionMap":{"java":{"insertions":76,"deletions":3}}},{"hash":"880679bdcb768ee3c3b62ea295cd69250df02f33","isMergeCommit":false,"messageTitle":"automated text ui testing","messageBody":"","tags":["A-TextUiTesting","A-TestUITesting"],"fileTypesAndContributionMap":{"txt":{"insertions":9,"deletions":0},"bat":{"insertions":1,"deletions":1},"sh":{"insertions":7,"deletions":4}}},{"hash":"7a49267bbcd1bd2005a0295b12b30be38ee06efc","isMergeCommit":false,"messageTitle":"Handle errors","messageBody":"","tags":["Level-5"],"fileTypesAndContributionMap":{"java":{"insertions":33,"deletions":4}}},{"hash":"1d8c26ec2e3db81c6d54b4423073cf7f35def76c","isMergeCommit":false,"messageTitle":"delete tasks","messageBody":"","tags":["Level-6"],"fileTypesAndContributionMap":{"java":{"insertions":10,"deletions":2}}}]},{"date":"2025-01-27","commitResults":[{"hash":"9790031ac0ea7834919a21105a88f156278211fe","isMergeCommit":false,"messageTitle":"adding storage to save list to device","messageBody":"","tags":["Level-7"],"fileTypesAndContributionMap":{"java":{"insertions":161,"deletions":67}}},{"hash":"85aace4d407efc828eb405de50c2effb8eec901b","isMergeCommit":false,"messageTitle":"formatting","messageBody":"","fileTypesAndContributionMap":{"java":{"insertions":0,"deletions":1}}},{"hash":"f5bb938ba531fd130069541bd1b836b5a0a194f7","isMergeCommit":false,"messageTitle":"spacing","messageBody":"","fileTypesAndContributionMap":{"java":{"insertions":2,"deletions":0}}},{"hash":"8c55d93a02f36f9a3d9fa51d40d37968064624b2","isMergeCommit":false,"messageTitle":"edit deadline class","messageBody":"","fileTypesAndContributionMap":{"java":{"insertions":1,"deletions":0}}},{"hash":"90289ce2773394bf154ae010530112389bdcac52","isMergeCommit":false,"messageTitle":"Revert \"edit deadline class\"","messageBody":"This reverts commit 8c55d93a02f36f9a3d9fa51d40d37968064624b2.\n","fileTypesAndContributionMap":{"java":{"insertions":0,"deletions":1}}},{"hash":"ea7afcd742d1eeada6f45faffbb4a0ce1563747c","isMergeCommit":true,"messageTitle":"Merge branch \u0027master\u0027 into branch-Level-7","messageBody":"","fileTypesAndContributionMap":{}},{"hash":"4659fd21c2cd59e603cf8e4ec3f2f71d63895e9c","isMergeCommit":false,"messageTitle":"create class Ui and Parser","messageBody":"","fileTypesAndContributionMap":{"java":{"insertions":8,"deletions":0}}},{"hash":"267b412a85132499968d5eac5170b9624b44c842","isMergeCommit":false,"messageTitle":"test branch","messageBody":"","fileTypesAndContributionMap":{"java":{"insertions":1,"deletions":0}}},{"hash":"064760325a5dda61b23915b4ed4ebe7b7d4b520d","isMergeCommit":false,"messageTitle":"ooppp","messageBody":"","fileTypesAndContributionMap":{"java":{"insertions":213,"deletions":123}}},{"hash":"265f97d0a13158db8d4c1c6e7d9ab7502e083231","isMergeCommit":false,"messageTitle":"Ui package","messageBody":"","tags":["A-Packages"],"fileTypesAndContributionMap":{"java":{"insertions":11,"deletions":11}}}]},{"date":"2025-01-28","commitResults":[{"hash":"a04a0d72c7e3d21820d8f474c7cd1e1b8dd7d8e9","isMergeCommit":false,"messageTitle":"using date time object instead of string","messageBody":"","fileTypesAndContributionMap":{"java":{"insertions":27,"deletions":6}}},{"hash":"c2e0d6f33ad5d24ce12e36eb1c08527215e8a3df","isMergeCommit":false,"messageTitle":"add \"date\" function to return all tasks due on input date","messageBody":"","tags":["Level-8"],"fileTypesAndContributionMap":{"java":{"insertions":53,"deletions":6}}},{"hash":"0bd137d845e7516c20e9557aef73dab63f009cec","isMergeCommit":false,"messageTitle":"spacing","messageBody":"","fileTypesAndContributionMap":{"java":{"insertions":1,"deletions":1}}},{"hash":"e40a50c23b90699fee118c71885848095d93faf1","isMergeCommit":false,"messageTitle":"Revert \"spacing\"","messageBody":"This reverts commit 0bd137d845e7516c20e9557aef73dab63f009cec.\n","fileTypesAndContributionMap":{"java":{"insertions":1,"deletions":1}}},{"hash":"b8c76725a608fb08dc6d12a664a5a8a3d5c77a15","isMergeCommit":true,"messageTitle":"Merge branch \u0027master\u0027 into branch-Level-8","messageBody":"* master:\n  Revert \"spacing\"\n  spacing\n","fileTypesAndContributionMap":{}},{"hash":"85a0dcfa36a3ea8ebb1908e43e86a5c53997b596","isMergeCommit":true,"messageTitle":"Merge commit \u002781a9c537afe8492675eb253968939364d65db091\u0027","messageBody":"* commit \u002781a9c537afe8492675eb253968939364d65db091\u0027:\n  build.gradle: Prevent generating a second JAR file\n  Bump gradle and lib version\n  Add Gradle support\n","fileTypesAndContributionMap":{}},{"hash":"07fb26e6c8289ad861d3ef345ec1df0094db1c85","isMergeCommit":true,"messageTitle":"Merge branch \u0027master\u0027 into branch-Level-8","messageBody":"* master:\n  build.gradle: Prevent generating a second JAR file\n  Bump gradle and lib version\n  Add Gradle support\n","fileTypesAndContributionMap":{}},{"hash":"db66378a1dc4088572682b1d8367c19b74d464bf","isMergeCommit":false,"messageTitle":"add \"find\" function that prints matching tasks to given keyword","messageBody":"","tags":["Level-9"],"fileTypesAndContributionMap":{"java":{"insertions":23,"deletions":0}}},{"hash":"53d19bbd09b51e835fb875a4cd94ba256c53fa96","isMergeCommit":false,"messageTitle":"Changes according to java coding standard","messageBody":"","tags":["A-CodingStandard"],"fileTypesAndContributionMap":{"java":{"insertions":53,"deletions":53}}},{"hash":"d8b92fc50ae669387beb3a00aa32df6fd4c01f48","isMergeCommit":false,"messageTitle":"Add javadoc for all non-private methods","messageBody":"","fileTypesAndContributionMap":{"java":{"insertions":97,"deletions":0}}},{"hash":"a9aa27a4d766e76a21f36591db29087a5c587624","isMergeCommit":false,"messageTitle":"Add comments","messageBody":"","fileTypesAndContributionMap":{"java":{"insertions":1,"deletions":0}}},{"hash":"2e7512e5b3066dffd142af32591d83dc5e647b9a","isMergeCommit":true,"messageTitle":"Merge branch \u0027branch-A-CodingStandard\u0027","messageBody":"* branch-A-CodingStandard:\n  Changes according to java coding standard\n","fileTypesAndContributionMap":{}},{"hash":"0557197e131d6245de94f1d748ec3a6fa8c0b7b4","isMergeCommit":true,"messageTitle":"Merge branch \u0027master\u0027 into branch-A-JavaDoc","messageBody":"* master:\n  Add comments\n  Changes according to java coding standard\n","tags":["A-JavaDoc"],"fileTypesAndContributionMap":{}},{"hash":"af54f6a45f944647ab147c75a072d0255ef594fb","isMergeCommit":true,"messageTitle":"Merge branch \u0027branch-Level-9\u0027","messageBody":"* branch-Level-9:\n  add \"find\" function that prints matching tasks to given keyword\n\n# Conflicts:\n#\tsrc/main/java/seb/ui/Sebastian.java\n","fileTypesAndContributionMap":{}},{"hash":"8769b0795a02ea62c31b4a087bdc08dd78002edd","isMergeCommit":true,"messageTitle":"Merge branch \u0027branch-A-JavaDoc\u0027","messageBody":"* branch-A-JavaDoc:\n  Add javadoc for all non-private methods\n","fileTypesAndContributionMap":{}},{"hash":"ee9eabc2108d56155e6dee15acb1d1f3d10bbba7","isMergeCommit":true,"messageTitle":"Merge branch \u0027branch-Level-8\u0027","messageBody":"* branch-Level-8:\n  add \"date\" function to return all tasks due on input date\n  using date time object instead of string\n\n# Conflicts:\n#\tsrc/main/java/seb/ui/Sebastian.java\n#\tsrc/main/java/seb/ui/TaskList.java\n#\tsrc/main/java/seb/ui/Ui.java\n","fileTypesAndContributionMap":{}},{"hash":"80b3bea2782d2dba445ed69072c791132a72cf07","isMergeCommit":false,"messageTitle":"variable changes","messageBody":"","fileTypesAndContributionMap":{"java":{"insertions":9,"deletions":45}}},{"hash":"8e3ee7cb49d0a86ef9a39770d67c06db02032c81","isMergeCommit":false,"messageTitle":"Add javadoc for parseDateTime() and parseShowDate() in Parser class","messageBody":"","fileTypesAndContributionMap":{"java":{"insertions":15,"deletions":0}}},{"hash":"8f24dc765e0a9b659624ce1e4ed73e30204024f2","isMergeCommit":false,"messageTitle":"Error handling in showDates() method for no tasks on given date returns different output message","messageBody":"","fileTypesAndContributionMap":{"java":{"insertions":19,"deletions":4}}},{"hash":"62668e628d9516a3c4ecc610b0515340268ed860","isMergeCommit":false,"messageTitle":"Add javadoc for find() method in Ui class","messageBody":"","fileTypesAndContributionMap":{"java":{"insertions":5,"deletions":0}}},{"hash":"e6ac7c21ab768b38961517721e01d2871f9441b7","isMergeCommit":false,"messageTitle":"Formatting of output","messageBody":"","fileTypesAndContributionMap":{"java":{"insertions":1,"deletions":0}}}]},{"date":"2025-01-30","commitResults":[{"hash":"011c16a6b90ec01488e5971be9092f6c1c542724","isMergeCommit":false,"messageTitle":"TaskList class: move showDates() method from TaskList to Ui class Ui class: edit showDates() to show number of tasks due Sebastian class: edit \"DATE\" switch case","messageBody":"","fileTypesAndContributionMap":{"gradle":{"insertions":9,"deletions":1},"java":{"insertions":32,"deletions":31}}}]},{"date":"2025-02-01","commitResults":[{"hash":"8998369b0e348cf52f397fa9a63a27562bac1314","isMergeCommit":false,"messageTitle":"test(TaskList): Add unit tests for TaskList methods","messageBody":"- Added JUnit tests for adding and removing tasks in TaskList\n- Ensured tasks are correctly stored and removed from the list\n- Used @BeforeEach to initialize a fresh TaskList instance before each test\n\nThese tests improve coverage and ensure TaskList behaves as expected\n","fileTypesAndContributionMap":{"java":{"insertions":35,"deletions":0}}},{"hash":"4435dd652491fdeea6cdf258c30c47a400f8bd6b","isMergeCommit":false,"messageTitle":"fix(Parser): Correct trimming logic in parseEvent method test(Parser): Add unit tests for parsing methods","messageBody":"- Fixed the for loop in parseEvent to properly trim and store values\n- Ensured correct splitting logic for event input format\n- Added JUnit tests in ParserTest to verify parseTodo, parseDeadline, and parseEvent behavior\n- Improved error handling for invalid event formats\n\nThis improves input parsing reliability and increases test coverage\n","tags":["A-Jar","A-JUnit"],"fileTypesAndContributionMap":{"java":{"insertions":34,"deletions":4}}},{"hash":"6ed236b15dded545838ca19733cb59a5d2faf419","isMergeCommit":false,"messageTitle":"Change jar file name in build.gradle","messageBody":"- Changed to seb.ui.Sebastian, where the main() method is found\n","fileTypesAndContributionMap":{"gradle":{"insertions":3,"deletions":4}}},{"hash":"ecf18b95305c9b8d0db537c089bc7802a8569dfe","isMergeCommit":false,"messageTitle":"style(checkstyle): Fix Checkstyle violations in codebase","messageBody":"- Updated code to comply with Checkstyle rules\n- Fixed indentation, naming conventions, and formatting issues\n- Ensured consistent coding style across the project\n\nThis improves code readability and maintainability.\n","fileTypesAndContributionMap":{"gradle":{"insertions":5,"deletions":0},"java":{"insertions":36,"deletions":34}}},{"hash":"1a145291f9b0df7013dd4cf9079c547f408a5e42","isMergeCommit":true,"messageTitle":"Merge tag \u0027A-CheckStyle\u0027","messageBody":"* tag \u0027A-CheckStyle\u0027:\n  chore(checkstyle): Add Checkstyle configuration files\n","fileTypesAndContributionMap":{}}]},{"date":"2025-02-05","commitResults":[{"hash":"2839da7e0bc2638a9a52268f64f1de869d084878","isMergeCommit":false,"messageTitle":"feat(gui): Add initial setup for GUI implementation","messageBody":"- Added `Main`, `Launcher`, and `DialogBox` classes for GUI integration\n- Updated `build.gradle` to support JavaFX dependencies\n- Added necessary images in `main/resources/images`\n- Prepared the project structure for future GUI enhancements\n\nThis sets up the foundation for the graphical user interface.\n","tags":["Level-10"],"fileTypesAndContributionMap":{"gradle":{"insertions":16,"deletions":1},"java":{"insertions":114,"deletions":0}}}]},{"date":"2025-02-06","commitResults":[{"hash":"7791a776ed40940b3d7de1c1435443ef73d7edba","isMergeCommit":false,"messageTitle":"feat(gui): Integrate FXML for MainWindow and DialogBox","messageBody":"- Added `MainWindow.fxml` and `DialogBox.fxml` for GUI layout\n- Updated `Main`, `Launcher`, and `DialogBox` classes to load FXML files\n- Improved UI structure for better separation of logic and presentation\n\nThis enhances the GUI by using FXML for better maintainability and scalability\n","fileTypesAndContributionMap":{"fxml":{"insertions":68,"deletions":0},"java":{"insertions":132,"deletions":74}}},{"hash":"de5cd9ab89c8e2a7455deba9a41862078a64b913","isMergeCommit":false,"messageTitle":"refactor(Sebastian): Capture Ui output for GUI integration","messageBody":"- Added `captureOutput()` method to redirect and capture `Ui` class prints\n- Updated `getResponse()` to use `Ui` methods without modifying them\n- Ensured `Sebastian` can return responses for both CLI and GUI\n- Preserved CLI functionality while enabling GUI interaction\n\nThis allows seamless integration of `Sebastian` with the GUI without altering `Ui` methods\n","fileTypesAndContributionMap":{"java":{"insertions":57,"deletions":34}}},{"hash":"c509c0be06613f3616a6802b2dfc3aff966d83b1","isMergeCommit":false,"messageTitle":"style(ui): Update Ui messages for more personality","messageBody":"- Enhanced messages for a friendlier tone\n- Refined task-related responses to be more engaging\n- Improved overall conversational feel of the assistant\n\nThese changes make interactions with Sebastian more lively and user-friendly\n","fileTypesAndContributionMap":{"java":{"insertions":7,"deletions":7}}},{"hash":"2442a0914ff97d9d85dfd75819af5aaa2abf3fec","isMergeCommit":true,"messageTitle":"Merge tag \u0027Level-10\u0027","messageBody":"* tag \u0027Level-10\u0027:\n  feat(gui): Add initial setup for GUI implementation\n","fileTypesAndContributionMap":{}},{"hash":"41853c8f9759de94a49c1625f0c16b69edfd0543","isMergeCommit":true,"messageTitle":"Merge tag \u0027Level-10\u0027","messageBody":"* tag \u0027Level-10\u0027:\n  refactor(Sebastian): Capture Ui output for GUI integration\n  feat(gui): Integrate FXML for MainWindow and DialogBox\n","fileTypesAndContributionMap":{}},{"hash":"21e4c948e50a2e2abdcd776bbf5e9f6be9050a8d","isMergeCommit":false,"messageTitle":"feat(gui): Integrate FXML for MainWindow and DialogBox","messageBody":"- Added `MainWindow.fxml` and `DialogBox.fxml` for GUI layout\n- Updated `Main`, `Launcher`, and `DialogBox` classes to load FXML files\n- Improved UI structure for better separation of logic and presentation\n\nThis enhances the GUI by using FXML for better maintainability and scalability\n","fileTypesAndContributionMap":{"fxml":{"insertions":68,"deletions":0},"java":{"insertions":132,"deletions":74}}},{"hash":"7f2d721bbfc8f23b573353a253e8fc8b70769630","isMergeCommit":false,"messageTitle":"refactor(Sebastian): Capture Ui output for GUI integration","messageBody":"- Added `captureOutput()` method to redirect and capture `Ui` class prints\n- Updated `getResponse()` to use `Ui` methods without modifying them\n- Ensured `Sebastian` can return responses for both CLI and GUI\n- Preserved CLI functionality while enabling GUI interaction\n\nThis allows seamless integration of `Sebastian` with the GUI without altering `Ui` methods\n","fileTypesAndContributionMap":{"java":{"insertions":57,"deletions":34}}},{"hash":"e5aa513d9d8d2fbebc167ef28f83b80c1630ddbb","isMergeCommit":false,"messageTitle":"style(ui): Update Ui messages for more personality","messageBody":"- Enhanced messages for a friendlier tone\n- Refined task-related responses to be more engaging\n- Improved overall conversational feel of the assistant\n\nThese changes make interactions with Sebastian more lively and user-friendly\n","fileTypesAndContributionMap":{"java":{"insertions":7,"deletions":7}}},{"hash":"0210d0e494d7c830dddeae7132f2f20d618f753f","isMergeCommit":false,"messageTitle":"feat(gui): Add Sebastian\u0027s photo to welcome message","messageBody":"- Updated `MainWindow` to display Sebastian\u0027s welcome message with his image on startup\n- Ensured `DialogBox` properly handles the welcome message format\n- Loaded `sebphoto.jpeg` from resources to maintain consistency with response messages\n\nThis improves the user experience by making the GUI more engaging\n","fileTypesAndContributionMap":{"java":{"insertions":71,"deletions":63}}}]},{"date":"2025-02-15","commitResults":[{"hash":"70e4032ed7556edfe9043460e5f92e0c7b4d757c","isMergeCommit":false,"messageTitle":"refactor: add assertions to document critical assumptions","messageBody":"Assertions have been added to key areas of the codebase to document\nassumptions that should always hold. This helps catch logic errors\nearly during development and improves code reliability\n","tags":["A-FullCommitMessage","A-Assertions"],"fileTypesAndContributionMap":{"java":{"insertions":20,"deletions":1}}},{"hash":"ceae336a8fc1d511d6048d6e34057e68d26693d0","isMergeCommit":false,"messageTitle":"refactor(storage): Improve code quality across classes","messageBody":"- Extracted task parsing logic into a new parseTaskLine method\n  to improve readability and maintainability.\n- Updated Javadoc comments for better clarity and consistency.\n- Added input validation in parseTaskLine to prevent\n  malformed task entries from causing runtime errors.\n\nThis refactoring makes loadTasks more modular and easier to\nextend in the future while maintaining robust error handling.\n","tags":["A-CodeQuality"],"fileTypesAndContributionMap":{"java":{"insertions":60,"deletions":23}}},{"hash":"6a19baad2d3a06259d57a5620a1cb9250d7ee5eb","isMergeCommit":true,"messageTitle":"Merge pull request #2 from crmlatte/branch-A-Assertions","messageBody":"refactor: add assertions to document critical assumptions","fileTypesAndContributionMap":{}},{"hash":"c393366ca7a381c296df98aa26c7d3a7fc80f452","isMergeCommit":true,"messageTitle":"Merge branch \u0027branch-A-CodeQuality\u0027","messageBody":"* branch-A-CodeQuality:\n  refactor(storage): Improve code quality across classes\n","fileTypesAndContributionMap":{}},{"hash":"586c1f7e6f2933c7d6ac6c1cad86480959e96828","isMergeCommit":true,"messageTitle":"Merge pull request #3 from crmlatte/branch-A-CodeQuality","messageBody":"refactor(storage): Improve code quality across classes","fileTypesAndContributionMap":{}},{"hash":"c0e7537a51065149a3356d458225fd8bbc683419","isMergeCommit":false,"messageTitle":"fix(parser): Correct date-time parsing for Event and Deadline","messageBody":"- Updated Parser logic to properly parse date-time inputs into\n  the correct LocalDateTime format.\n- Ensured consistent date-time formatting when creating new Event\n  and Deadline tasks.\n\nThis fixes inconsistencies in date-time parsing, improving\ntask creation accuracy and user experience.\n","fileTypesAndContributionMap":{"java":{"insertions":3,"deletions":0}}},{"hash":"b61b680c21dba6337b2e899a8e13d05df022b2b6","isMergeCommit":false,"messageTitle":"feat: Add update command to edit existing tasks","messageBody":"- Implemented UPDATE command in Sebastian to allow users to modify\n  the description of existing tasks.\n- Prompted users for a second input to enter the new task description.\n- Added update method to Task to support updates.\n- Ensured tasks are updated and saved correctly in Storage.\n\nThis enhances task management by allowing users to modify tasks\nwithout deleting and recreating them.\n","tags":["jar-v.02","BCD-Extension"],"fileTypesAndContributionMap":{"java":{"insertions":102,"deletions":0}}}]},{"date":"2025-02-16","commitResults":[{"hash":"b4d46598ca6d39fa0a26769615ee801e4a43b799","isMergeCommit":false,"messageTitle":"feat(parser): add date-time validation in checkDateValidity","messageBody":"- Implemented checkDateValidity method in Parser class.\n- Ensures that dates are not in the past.\n- Ensures that the start date is not after the end date.\n","tags":["A-MoreErrorHandling"],"fileTypesAndContributionMap":{"java":{"insertions":50,"deletions":12}}},{"hash":"457a60743fe6104fa48d4598ee54a6abe0321e93","isMergeCommit":false,"messageTitle":"test: add TaskTest for update method and expand ParserTest for checkDateValidity","messageBody":"- Added TaskTest class to test the update method in Task class.\n- Covered cases for updating description, valid deadlines, past deadlines, and invalid fields.\n- Added more test cases in ParserTest to validate checkDateValidity method.\n- Ensured robust exception handling and date validation.\n","tags":["A-MoreTesting"],"fileTypesAndContributionMap":{"java":{"insertions":60,"deletions":1}}}]}]},"authorFileTypeContributionMap":{"crmlatte":{"java":1155,"md":0,"fxml":68,"sh":7,"bat":1,"gradle":31,"txt":9}},"authorContributionVariance":{"crmlatte":33759.96},"authorDisplayNameMap":{"crmlatte":"CS2103T-W12-4 SULA..HNAN"}}
