{"authorDailyContributionsMap":{"Jensen188":[{"date":"2025-01-24","commitResults":[{"hash":"1434fe531c06bb9285f025de8b9b9d4e3a2d8362","isMergeCommit":false,"messageTitle":"Rename Duke.java","messageBody":"","tags":["Level-0"],"fileTypesAndContributionMap":{"java":{"insertions":23,"deletions":10}}}]},{"date":"2025-01-26","commitResults":[{"hash":"2384bcc6e0661c376baa5dc4260c343d0748b05b","isMergeCommit":false,"messageTitle":"Add echo function to Pikachu.java","messageBody":"","tags":["Level-1"],"fileTypesAndContributionMap":{"java":{"insertions":28,"deletions":3}}},{"hash":"231fad535c8891053e22f910d9bea3d214cfa602","isMergeCommit":false,"messageTitle":"Create a list to save and display tasks","messageBody":"","tags":["Level-2"],"fileTypesAndContributionMap":{"java":{"insertions":28,"deletions":13}}},{"hash":"17bb91b6a7fc60cebe5180330d6bf2b8ae533728","isMergeCommit":false,"messageTitle":"Create Task.java to manage task","messageBody":"","fileTypesAndContributionMap":{"java":{"insertions":26,"deletions":0}}},{"hash":"c66d0a021feeb67826bc277f0e97acc2417aa08a","isMergeCommit":false,"messageTitle":"Add mark and unmark task function to Pikachu.java","messageBody":"","tags":["Level-3"],"fileTypesAndContributionMap":{"java":{"insertions":37,"deletions":15}}}]},{"date":"2025-01-31","commitResults":[{"hash":"007445f3f1d87f12ff0a149d8846716b42b50038","isMergeCommit":false,"messageTitle":"Add three subclasses of Task.java","messageBody":"","tags":["Level-4"],"fileTypesAndContributionMap":{"java":{"insertions":97,"deletions":16}}},{"hash":"dc90b98f82ec6ed39a065ff1b0236d9344eeccd8","isMergeCommit":false,"messageTitle":"Modify runtest.bat for automated text UI testing","messageBody":"","tags":["A-TextUiTesting"],"fileTypesAndContributionMap":{"txt":{"insertions":7,"deletions":0},"java":{"insertions":0,"deletions":2},"bat":{"insertions":1,"deletions":1},"sh":{"insertions":0,"deletions":38}}},{"hash":"4fa68a281fc68e503abb36e383600abe5570ee1e","isMergeCommit":false,"messageTitle":"Handle few errors in Pikachu.java","messageBody":"","tags":["Level-5"],"fileTypesAndContributionMap":{"java":{"insertions":35,"deletions":9}}},{"hash":"439f3cb1e772dd5f58bffe19292cc338c0b6e86e","isMergeCommit":false,"messageTitle":"Add delete function to Pikachu.java","messageBody":"","tags":["Level-6"],"fileTypesAndContributionMap":{"java":{"insertions":8,"deletions":0}}}]}]},"authorFileTypeContributionMap":{"Jensen188":{"java":224,"md":0,"fxml":0,"sh":0,"bat":1,"gradle":0,"txt":7}},"authorContributionVariance":{"Jensen188":2828.225},"authorDisplayNameMap":{"Jensen188":"CS2103T-T08-1 TEO ..NSEN"}}
